{"2024-01-22-2024-01-22": {"MEX - Alejeandro Armenta - FB": [{"valor": 365, "palabra": "alejandro-armenta"}, {"valor": 65, "palabra": "coordinador-alejandro"}, {"valor": 44, "palabra": "armenta-gracias"}, {"valor": 44, "palabra": "maestro-alejandro"}, {"valor": 36, "palabra": "claudia-sheinbaum"}, {"valor": 33, "palabra": "senador-alejandro"}, {"valor": 22, "palabra": "armenta-siempre"}, {"valor": 17, "palabra": "armenta-alejandro"}, {"valor": 15, "palabra": "nuestros-abuelos"}, {"valor": 14, "palabra": "armenta-juntos"}, {"valor": 13, "palabra": "armenta-admiramos"}, {"valor": 12, "palabra": "gracias-senador"}, {"valor": 12, "palabra": "armenta-liderazgo"}, {"valor": 12, "palabra": "armenta-claudia"}, {"valor": 11, "palabra": "armenta-coordinador"}, {"valor": 11, "palabra": "contra-violencia"}, {"valor": 10, "palabra": "gracias-compartir"}, {"valor": 10, "palabra": "puebla-alejandro"}, {"valor": 10, "palabra": "senador-armenta"}, {"valor": 10, "palabra": "armenta-compromiso"}, {"valor": 10, "palabra": "sheinbaum-coordinador"}, {"valor": 9, "palabra": "adultos-mayores"}, {"valor": 9, "palabra": "violencia-contra"}, {"valor": 8, "palabra": "erradicar-violencia"}, {"valor": 8, "palabra": "sheinbaum-alejandro"}, {"valor": 7, "palabra": "gracias-alejandro"}, {"valor": 7, "palabra": "armenta-trabajo"}, {"valor": 7, "palabra": "nuestra-conexión"}, {"valor": 7, "palabra": "conexión-ancestral"}, {"valor": 7, "palabra": "puebla-fuerte"}], "MEX - Fernando Morales - FB": [{"valor": 1, "palabra": "oportunidad-visitar"}, {"valor": 1, "palabra": "visitar-colonia"}, {"valor": 1, "palabra": "colonia-barranca"}, {"valor": 1, "palabra": "barranca-municipio"}, {"valor": 1, "palabra": "municipio-puebla"}, {"valor": 1, "palabra": "puebla-increíble"}, {"valor": 1, "palabra": "increíble-comunidades"}, {"valor": 1, "palabra": "comunidades-marginadas"}, {"valor": 1, "palabra": "marginadas-dentro"}, {"valor": 1, "palabra": "dentro-capital"}, {"valor": 1, "palabra": "capital-estado"}, {"valor": 1, "palabra": "estado-invisiblicemos"}, {"valor": 1, "palabra": "invisiblicemos-comunidades"}, {"valor": 1, "palabra": "comunidades-olvidadas"}, {"valor": 1, "palabra": "olvidadas-muchos"}, {"valor": 1, "palabra": "muchos-saludos"}, {"valor": 1, "palabra": "saludos-conocen"}, {"valor": 1, "palabra": "conocen-jajajaja"}, {"valor": 1, "palabra": "jajajaja-apenas"}, {"valor": 1, "palabra": "apenas-cuenta"}, {"valor": 1, "palabra": "cuenta-fernando"}, {"valor": 1, "palabra": "fernando-máximo"}, {"valor": 1, "palabra": "máximo-descubriste"}, {"valor": 1, "palabra": "descubriste-felicidades"}], "MEX - Eduardo Rivera - FB": [{"valor": 25, "palabra": "eduardo-rivera"}, {"valor": 8, "palabra": "gobernador-puebla"}, {"valor": 8, "palabra": "próximo-gobernador"}, {"valor": 6, "palabra": "rivera-gobernador"}, {"valor": 5, "palabra": "puebla-eduardo"}, {"valor": 5, "palabra": "gobernador-gobernador"}, {"valor": 4, "palabra": "preocupa-estado"}, {"valor": 4, "palabra": "tantita-cucaracha"}, {"valor": 3, "palabra": "nuestro-gobernador"}, {"valor": 3, "palabra": "rivera-próximo"}, {"valor": 2, "palabra": "estado-puebla"}, {"valor": 2, "palabra": "nuestro-estado"}, {"valor": 2, "palabra": "mujeres-emprendedoras"}, {"valor": 2, "palabra": "alguna-eduardo"}, {"valor": 2, "palabra": "estamos-contigo"}, {"valor": 2, "palabra": "rivera-puebla"}, {"valor": 2, "palabra": "valerio-armenta"}, {"valor": 2, "palabra": "queremos-gobernador"}, {"valor": 2, "palabra": "xóchitl-presidenta"}, {"valor": 2, "palabra": "presidenta-eduardo"}, {"valor": 2, "palabra": "presidente-municipal"}, {"valor": 2, "palabra": "estado-tantita"}, {"valor": 2, "palabra": "cucaracha-miserable"}, {"valor": 2, "palabra": "miserable-verdad"}, {"valor": 2, "palabra": "verdad-tantitos"}, {"valor": 2, "palabra": "tantitos-huevos"}, {"valor": 2, "palabra": "huevos-colibrí"}, {"valor": 2, "palabra": "colibrí-preocupa"}, {"valor": 2, "palabra": "estado-amante"}, {"valor": 2, "palabra": "amante-puesto"}]}, "2024-01-23-2024-01-23": {"MEX - Alejeandro Armenta - FB": [{"valor": 329, "palabra": "alejandro-armenta"}, {"valor": 61, "palabra": "pueblos-indígenas"}, {"valor": 40, "palabra": "senador-alejandro"}, {"valor": 27, "palabra": "nuestros-pueblos"}, {"valor": 24, "palabra": "armenta-gobernador"}, {"valor": 23, "palabra": "próximo-gobernador"}, {"valor": 23, "palabra": "armenta-gracias"}, {"valor": 19, "palabra": "saludos-senador"}, {"valor": 17, "palabra": "armenta-puebla"}, {"valor": 16, "palabra": "gobernador-puebla"}, {"valor": 15, "palabra": "puebla-alejandro"}, {"valor": 14, "palabra": "senador-armenta"}, {"valor": 14, "palabra": "coordinador-alejandro"}, {"valor": 14, "palabra": "bienvenido-benito"}, {"valor": 13, "palabra": "trabajo-alejandro"}, {"valor": 13, "palabra": "benito-puebla"}, {"valor": 12, "palabra": "armenta-liderazgo"}, {"valor": 11, "palabra": "mujeres-transformadoras"}, {"valor": 11, "palabra": "armenta-siempre"}, {"valor": 11, "palabra": "llegada-benito"}, {"valor": 10, "palabra": "senado-alejandro"}, {"valor": 10, "palabra": "armenta-compromiso"}, {"valor": 10, "palabra": "armenta-alejandro"}, {"valor": 10, "palabra": "puebla-armenta"}, {"valor": 10, "palabra": "armenta-mujeres"}, {"valor": 10, "palabra": "nuestro-próximo"}, {"valor": 9, "palabra": "proyectos-senado"}, {"valor": 9, "palabra": "armenta-estamos"}, {"valor": 9, "palabra": "gracias-alejandro"}, {"valor": 9, "palabra": "gracias-compromiso"}], "MEX - Fernando Morales - FB": [], "MEX - Eduardo Rivera - FB": [{"valor": 30, "palabra": "eduardo-rivera"}, {"valor": 10, "palabra": "próximo-gobernador"}, {"valor": 9, "palabra": "rivera-gobernador"}, {"valor": 9, "palabra": "gobernador-puebla"}, {"valor": 7, "palabra": "estado-puebla"}, {"valor": 5, "palabra": "nuestro-estado"}, {"valor": 4, "palabra": "auxiliar-grande"}, {"valor": 4, "palabra": "gobernador-eduardo"}, {"valor": 3, "palabra": "gracias-visita"}, {"valor": 3, "palabra": "rivera-próximo"}, {"valor": 3, "palabra": "nuestro-próximo"}, {"valor": 3, "palabra": "xóchitl-presidenta"}, {"valor": 3, "palabra": "presidenta-eduardo"}, {"valor": 3, "palabra": "eduardo-gobernador"}, {"valor": 3, "palabra": "mejorando-seguro"}, {"valor": 3, "palabra": "seguro-decisión"}, {"valor": 3, "palabra": "decisión-tomado"}, {"valor": 3, "palabra": "tomado-créanme"}, {"valor": 3, "palabra": "créanme-ganado"}, {"valor": 3, "palabra": "ganado-imagino"}, {"valor": 3, "palabra": "imagino-estado"}, {"valor": 3, "palabra": "estado-invirtiendo"}, {"valor": 3, "palabra": "invirtiendo-plataforma"}, {"valor": 3, "palabra": "plataforma-ayudado"}, {"valor": 3, "palabra": "ayudado-plataforma"}, {"valor": 3, "palabra": "plataforma-interesado"}, {"valor": 3, "palabra": "interesado-necesita"}, {"valor": 3, "palabra": "necesita-información"}, {"valor": 3, "palabra": "información-funciona"}, {"valor": 3, "palabra": "funciona-envíele"}]}, "2024-01-24-2024-01-24": {"MEX - Alejeandro Armenta - FB": [{"valor": 370, "palabra": "alejandro-armenta"}, {"valor": 90, "palabra": "felicidades-senador"}, {"valor": 89, "palabra": "muchas-felicidades"}, {"valor": 81, "palabra": "senador-alejandro"}, {"valor": 46, "palabra": "próximo-gobernador"}, {"valor": 33, "palabra": "armenta-alejandro"}, {"valor": 27, "palabra": "gobernador-puebla"}, {"valor": 26, "palabra": "comunidad-digital"}, {"valor": 22, "palabra": "violencia-digital"}, {"valor": 21, "palabra": "armenta-gracias"}, {"valor": 16, "palabra": "senador-armenta"}, {"valor": 16, "palabra": "armenta-gobernador"}, {"valor": 16, "palabra": "nuestro-próximo"}, {"valor": 16, "palabra": "felicidades-alejandro"}, {"valor": 15, "palabra": "puebla-felicidades"}, {"valor": 14, "palabra": "armenta-felicidades"}, {"valor": 13, "palabra": "inteligencia-artificial"}, {"valor": 13, "palabra": "armenta-puebla"}, {"valor": 13, "palabra": "senador-felicidades"}, {"valor": 12, "palabra": "gracias-senador"}, {"valor": 12, "palabra": "internacional-educación"}, {"valor": 12, "palabra": "armenta-senador"}, {"valor": 12, "palabra": "cambio-positivo"}, {"valor": 12, "palabra": "creatividad-comunidad"}, {"valor": 12, "palabra": "senador-muchas"}, {"valor": 12, "palabra": "armenta-muchas"}, {"valor": 11, "palabra": "armenta-compromiso"}, {"valor": 11, "palabra": "digital-alejandro"}, {"valor": 11, "palabra": "felicidades-felicidades"}, {"valor": 11, "palabra": "coordinador-alejandro"}], "MEX - Fernando Morales - FB": [], "MEX - Eduardo Rivera - FB": [{"valor": 26, "palabra": "eduardo-rivera"}, {"valor": 17, "palabra": "próximo-gobernador"}, {"valor": 12, "palabra": "gobernador-puebla"}, {"valor": 7, "palabra": "gobernador-eduardo"}, {"valor": 6, "palabra": "nuestro-próximo"}, {"valor": 6, "palabra": "estado-puebla"}, {"valor": 6, "palabra": "rivera-gobernador"}, {"valor": 5, "palabra": "rivera-próximo"}, {"valor": 5, "palabra": "muchas-felicidades"}, {"valor": 3, "palabra": "puebla-rivera"}, {"valor": 3, "palabra": "puebla-gobernador"}, {"valor": 3, "palabra": "puebla-eduardo"}, {"valor": 3, "palabra": "gobernador-estado"}, {"valor": 3, "palabra": "gobernador-saludos"}, {"valor": 3, "palabra": "podrás-derotar"}, {"valor": 2, "palabra": "rivera-nuestro"}, {"valor": 2, "palabra": "puebla-saludos"}, {"valor": 2, "palabra": "puebla-próximo"}, {"valor": 2, "palabra": "puebla-nuestro"}, {"valor": 2, "palabra": "acción-nacional"}, {"valor": 2, "palabra": "ciudad-puebla"}, {"valor": 2, "palabra": "puebla-capital"}, {"valor": 2, "palabra": "puebla-felicidades"}, {"valor": 2, "palabra": "futuro-gobernador"}, {"valor": 2, "palabra": "eduardo-gobernador"}, {"valor": 2, "palabra": "saludos-próximo"}, {"valor": 2, "palabra": "xóchitl-presidenta"}, {"valor": 2, "palabra": "presidenta-eduardo"}, {"valor": 2, "palabra": "rivera-pavimentar"}, {"valor": 2, "palabra": "pavimentar-palmas"}]}, "2024-01-25-2024-01-25": {"MEX - Alejeandro Armenta - FB": [{"valor": 263, "palabra": "alejandro-armenta"}, {"valor": 70, "palabra": "senador-alejandro"}, {"valor": 36, "palabra": "felicidades-senador"}, {"valor": 36, "palabra": "muchas-felicidades"}, {"valor": 22, "palabra": "armenta-alejandro"}, {"valor": 16, "palabra": "próximo-gobernador"}, {"valor": 15, "palabra": "gobernador-puebla"}, {"valor": 14, "palabra": "violencia-género"}, {"valor": 14, "palabra": "armenta-admirable"}, {"valor": 13, "palabra": "seguridad-bienestar"}, {"valor": 13, "palabra": "bienestar-mujeres"}, {"valor": 13, "palabra": "armenta-gracias"}, {"valor": 12, "palabra": "erradicar-violencia"}, {"valor": 12, "palabra": "mujeres-alejandro"}, {"valor": 12, "palabra": "contra-violencia"}, {"valor": 11, "palabra": "mujeres-senador"}, {"valor": 11, "palabra": "puebla-alejandro"}, {"valor": 11, "palabra": "armenta-gobernador"}, {"valor": 10, "palabra": "armenta-puebla"}, {"valor": 10, "palabra": "seguridad-mujeres"}, {"valor": 10, "palabra": "senador-armenta"}, {"valor": 10, "palabra": "coordinador-alejandro"}, {"valor": 9, "palabra": "violencia-contra"}, {"valor": 9, "palabra": "gracias-senador"}, {"valor": 9, "palabra": "armenta-felicidades"}, {"valor": 8, "palabra": "senado-república"}, {"valor": 8, "palabra": "excelente-trabajo"}, {"valor": 8, "palabra": "proteger-mujeres"}, {"valor": 7, "palabra": "inteligencia-artificial"}, {"valor": 7, "palabra": "armenta-liderazgo"}], "MEX - Fernando Morales - FB": [], "MEX - Eduardo Rivera - FB": [{"valor": 28, "palabra": "próximo-gobernador"}, {"valor": 26, "palabra": "eduardo-rivera"}, {"valor": 23, "palabra": "muchas-felicidades"}, {"valor": 12, "palabra": "gobernador-puebla"}, {"valor": 11, "palabra": "rivera-gobernador"}, {"valor": 8, "palabra": "nuestro-próximo"}, {"valor": 8, "palabra": "gobernador-gobernador"}, {"valor": 6, "palabra": "puebla-eduardo"}, {"valor": 6, "palabra": "felicidades-eduardo"}, {"valor": 5, "palabra": "gobernador-muchas"}, {"valor": 5, "palabra": "felicidades-nuestro"}, {"valor": 5, "palabra": "puebla-felicidades"}, {"valor": 5, "palabra": "futuro-gobernador"}, {"valor": 4, "palabra": "estado-puebla"}, {"valor": 4, "palabra": "felicidades-próximo"}, {"valor": 4, "palabra": "estamos-contigo"}, {"valor": 4, "palabra": "rivera-próximo"}, {"valor": 3, "palabra": "gobernador-contigo"}, {"valor": 3, "palabra": "excelente-gobernador"}, {"valor": 3, "palabra": "corregir-estado"}, {"valor": 3, "palabra": "puebla-muchas"}, {"valor": 3, "palabra": "rivera-muchas"}, {"valor": 3, "palabra": "estamos-listos"}, {"valor": 3, "palabra": "gobernador-nuestro"}, {"valor": 3, "palabra": "gobernador-rivera"}, {"valor": 3, "palabra": "cambio-puebla"}, {"valor": 3, "palabra": "gobernador-eduardo"}, {"valor": 3, "palabra": "xóchitl-presidenta"}, {"valor": 3, "palabra": "presidenta-eduardo"}, {"valor": 2, "palabra": "contigo-muchas"}]}, "2024-01-26-2024-01-26": {"MEX - Alejeandro Armenta - FB": [{"valor": 240, "palabra": "alejandro-armenta"}, {"valor": 65, "palabra": "senador-alejandro"}, {"valor": 34, "palabra": "saludos-senador"}, {"valor": 25, "palabra": "fuerte-abrazo"}, {"valor": 23, "palabra": "próximo-gobernador"}, {"valor": 18, "palabra": "senador-armenta"}, {"valor": 17, "palabra": "gobernador-puebla"}, {"valor": 17, "palabra": "futuro-gobernador"}, {"valor": 15, "palabra": "cambio-positivo"}, {"valor": 15, "palabra": "armenta-saludos"}, {"valor": 14, "palabra": "nuestros-padres"}, {"valor": 13, "palabra": "estamos-listos"}, {"valor": 12, "palabra": "nuestro-próximo"}, {"valor": 11, "palabra": "trabajo-senador"}, {"valor": 11, "palabra": "armenta-estamos"}, {"valor": 10, "palabra": "armenta-excelente"}, {"valor": 10, "palabra": "armenta-gobernador"}, {"valor": 10, "palabra": "muchas-felicidades"}, {"valor": 9, "palabra": "armenta-alejandro"}, {"valor": 9, "palabra": "armenta-gracias"}, {"valor": 9, "palabra": "saludos-alejandro"}, {"valor": 8, "palabra": "felicidades-senador"}, {"valor": 8, "palabra": "excelente-semana"}, {"valor": 8, "palabra": "gracias-senador"}, {"valor": 8, "palabra": "puebla-fuerte"}, {"valor": 8, "palabra": "armenta-lidera"}, {"valor": 8, "palabra": "senador-saludos"}, {"valor": 8, "palabra": "bendiciones-saludos"}, {"valor": 8, "palabra": "bendiciones-senador"}, {"valor": 7, "palabra": "estamos-alejandro"}], "MEX - Fernando Morales - FB": [], "MEX - Eduardo Rivera - FB": [{"valor": 33, "palabra": "eduardo-rivera"}, {"valor": 15, "palabra": "muchas-felicidades"}, {"valor": 13, "palabra": "próximo-gobernador"}, {"valor": 9, "palabra": "gobernador-puebla"}, {"valor": 8, "palabra": "rivera-gobernador"}, {"valor": 5, "palabra": "xóchitl-eduardo"}, {"valor": 4, "palabra": "felicidades-eduardo"}, {"valor": 4, "palabra": "rivera-próximo"}, {"valor": 4, "palabra": "estado-puebla"}, {"valor": 4, "palabra": "rivera-muchas"}, {"valor": 4, "palabra": "gobernador-eduardo"}, {"valor": 4, "palabra": "hagamos-méxico"}, {"valor": 4, "palabra": "méxico-despeje"}, {"valor": 4, "palabra": "despeje-claudiquemos"}, {"valor": 3, "palabra": "diputada-federal"}, {"valor": 3, "palabra": "aranda-orozco"}, {"valor": 3, "palabra": "gobernador-saludos"}, {"valor": 3, "palabra": "futuro-gobernador"}, {"valor": 3, "palabra": "gobernador-gobernador"}, {"valor": 3, "palabra": "rivera-eduardo"}, {"valor": 3, "palabra": "nuestro-próximo"}, {"valor": 3, "palabra": "felicidades-bendiga"}, {"valor": 3, "palabra": "claudiquemos-xóchitl"}, {"valor": 2, "palabra": "constancia-acredita"}, {"valor": 2, "palabra": "acredita-candidato"}, {"valor": 2, "palabra": "candidato-puebla"}, {"valor": 2, "palabra": "puebla-gubernatura"}, {"valor": 2, "palabra": "gubernatura-estado"}, {"valor": 2, "palabra": "presidente-municipal"}, {"valor": 2, "palabra": "genoveva-huerta"}]}, "2024-01-27-2024-01-27": {"MEX - Alejeandro Armenta - FB": [{"valor": 164, "palabra": "alejandro-armenta"}, {"valor": 36, "palabra": "saludos-senador"}, {"valor": 34, "palabra": "senador-alejandro"}, {"valor": 24, "palabra": "próximo-gobernador"}, {"valor": 23, "palabra": "armenta-saludos"}, {"valor": 23, "palabra": "armenta-gobernador"}, {"valor": 20, "palabra": "coordinador-alejandro"}, {"valor": 18, "palabra": "gobernador-puebla"}, {"valor": 17, "palabra": "armenta-alejandro"}, {"valor": 14, "palabra": "coordinador-armenta"}, {"valor": 14, "palabra": "puebla-saludos"}, {"valor": 12, "palabra": "futuro-gobernador"}, {"valor": 10, "palabra": "senador-saludos"}, {"valor": 10, "palabra": "senador-armenta"}, {"valor": 9, "palabra": "gobernador-saludos"}, {"valor": 9, "palabra": "fuerte-abrazo"}, {"valor": 8, "palabra": "armenta-felicidades"}, {"valor": 8, "palabra": "gobernador-alejandro"}, {"valor": 7, "palabra": "puebla-senador"}, {"valor": 7, "palabra": "felicidades-senador"}, {"valor": 7, "palabra": "excelente-senador"}, {"valor": 7, "palabra": "saludos-alejandro"}, {"valor": 7, "palabra": "nuestro-próximo"}, {"valor": 6, "palabra": "estación-ixtepec"}, {"valor": 6, "palabra": "muchas-felicidades"}, {"valor": 6, "palabra": "gracias-senador"}, {"valor": 6, "palabra": "armenta-gracias"}, {"valor": 6, "palabra": "armenta-excelente"}, {"valor": 5, "palabra": "saludos-saludos"}, {"valor": 5, "palabra": "armenta-senador"}], "MEX - Fernando Morales - FB": [], "MEX - Eduardo Rivera - FB": [{"valor": 19, "palabra": "eduardo-rivera"}, {"valor": 8, "palabra": "rivera-gobernador"}, {"valor": 8, "palabra": "próximo-gobernador"}, {"valor": 5, "palabra": "armenta-gobernador"}, {"valor": 5, "palabra": "gobernador-puebla"}, {"valor": 4, "palabra": "nuestro-próximo"}, {"valor": 4, "palabra": "muchas-felicidades"}, {"valor": 3, "palabra": "estado-puebla"}, {"valor": 3, "palabra": "hagamos-méxico"}, {"valor": 3, "palabra": "méxico-despeje"}, {"valor": 3, "palabra": "despeje-claudiquemos"}, {"valor": 3, "palabra": "claudiquemos-xóchitl"}, {"valor": 3, "palabra": "xóchitl-eduardo"}, {"valor": 3, "palabra": "siempre-mismos"}, {"valor": 3, "palabra": "alguna-eduardo"}, {"valor": 2, "palabra": "zambrano-grijalva"}, {"valor": 2, "palabra": "amanecer-puebla"}, {"valor": 2, "palabra": "méxico-posible"}, {"valor": 2, "palabra": "puebla-dirección"}, {"valor": 2, "palabra": "dirección-ejecutiva"}, {"valor": 2, "palabra": "repetir-genoveva"}, {"valor": 2, "palabra": "genoveva-puebla"}, {"valor": 2, "palabra": "puebla-diputada"}, {"valor": 2, "palabra": "genoveva-huerta"}, {"valor": 2, "palabra": "mismos-siempre"}, {"valor": 2, "palabra": "rivera-próximo"}, {"valor": 2, "palabra": "rivera-victoria"}, {"valor": 2, "palabra": "eduardo-gobernador"}, {"valor": 2, "palabra": "gobernador-felicidades"}, {"valor": 2, "palabra": "cambio-tranquilidad"}]}, "2024-01-28-2024-01-28": {"MEX - Alejeandro Armenta - FB": [{"valor": 91, "palabra": "alejandro-armenta"}, {"valor": 9, "palabra": "senador-alejandro"}, {"valor": 9, "palabra": "armenta-admirable"}, {"valor": 8, "palabra": "armenta-disfrute"}, {"valor": 7, "palabra": "mujeres-alejandro"}, {"valor": 7, "palabra": "armenta-alejandro"}, {"valor": 6, "palabra": "armenta-impulsando"}, {"valor": 6, "palabra": "grandes-proyectos"}, {"valor": 5, "palabra": "puebla-alejandro"}, {"valor": 5, "palabra": "armenta-familia"}, {"valor": 5, "palabra": "compromiso-erradicación"}, {"valor": 5, "palabra": "erradicación-violencia"}, {"valor": 5, "palabra": "reforma-constitucional"}, {"valor": 5, "palabra": "gracias-senador"}, {"valor": 5, "palabra": "admirable-compromiso"}, {"valor": 5, "palabra": "progreso-puebla"}, {"valor": 5, "palabra": "visión-futuro"}, {"valor": 5, "palabra": "futuro-siempre"}, {"valor": 5, "palabra": "siempre-liderando"}, {"valor": 5, "palabra": "liderando-grandes"}, {"valor": 5, "palabra": "proyectos-méxico"}, {"valor": 5, "palabra": "visión-transformadora"}, {"valor": 5, "palabra": "transformadora-puebla"}, {"valor": 4, "palabra": "violencia-contra"}, {"valor": 4, "palabra": "contra-mujeres"}, {"valor": 4, "palabra": "proteger-mujeres"}, {"valor": 4, "palabra": "armenta-gracias"}, {"valor": 4, "palabra": "armenta-gobernador"}, {"valor": 4, "palabra": "puebla-excelente"}, {"valor": 4, "palabra": "impulsando-progreso"}], "MEX - Fernando Morales - FB": [{"valor": 1, "palabra": "iniciativa-armonización"}, {"valor": 1, "palabra": "armonización-justicia"}, {"valor": 1, "palabra": "justicia-violencia"}, {"valor": 1, "palabra": "violencia-vicaria"}, {"valor": 1, "palabra": "vicaria-presentamos"}, {"valor": 1, "palabra": "presentamos-jueves"}, {"valor": 1, "palabra": "jueves-compromiso"}, {"valor": 1, "palabra": "compromiso-proteger"}, {"valor": 1, "palabra": "proteger-mujeres"}, {"valor": 1, "palabra": "mujeres-esencial"}, {"valor": 1, "palabra": "esencial-sociedad"}, {"valor": 1, "palabra": "sociedad-segura"}, {"valor": 1, "palabra": "segura-tuvimos"}, {"valor": 1, "palabra": "tuvimos-taller"}, {"valor": 1, "palabra": "taller-capacitación"}, {"valor": 1, "palabra": "capacitación-materia"}, {"valor": 1, "palabra": "materia-electoral"}, {"valor": 1, "palabra": "electoral-comunicación"}, {"valor": 1, "palabra": "comunicación-miembros"}], "MEX - Eduardo Rivera - FB": [{"valor": 20, "palabra": "eduardo-rivera"}, {"valor": 7, "palabra": "xóchitl-gálvez"}, {"valor": 5, "palabra": "puebla-eduardo"}, {"valor": 4, "palabra": "rivera-gobernador"}, {"valor": 4, "palabra": "gobernador-gobernador"}, {"valor": 3, "palabra": "gustavo-magaña"}, {"valor": 3, "palabra": "rivera-puebla"}, {"valor": 3, "palabra": "corregir-puebla"}, {"valor": 2, "palabra": "trabajar-méxico"}, {"valor": 2, "palabra": "méxico-gobernador"}, {"valor": 2, "palabra": "armenta-gobernador"}, {"valor": 2, "palabra": "federal-distrito"}, {"valor": 2, "palabra": "seguirás-trabajando"}, {"valor": 2, "palabra": "puebla-rivera"}, {"valor": 2, "palabra": "futuro-gobernador"}, {"valor": 2, "palabra": "priandejos-desgraciaron"}, {"valor": 2, "palabra": "desgraciaron-méxico"}, {"valor": 2, "palabra": "xóchitl-presidenta"}, {"valor": 2, "palabra": "hagamos-méxico"}, {"valor": 2, "palabra": "méxico-despeje"}, {"valor": 2, "palabra": "despeje-claudiquemos"}, {"valor": 2, "palabra": "claudiquemos-xóchitl"}, {"valor": 2, "palabra": "xóchitl-eduardo"}, {"valor": 2, "palabra": "claudia-rivera"}, {"valor": 2, "palabra": "gálvez-eduardo"}, {"valor": 2, "palabra": "próximo-gobernador"}, {"valor": 2, "palabra": "gobernador-rivera"}, {"valor": 2, "palabra": "gobernador-puebla"}, {"valor": 1, "palabra": "fuerza-valentía"}, {"valor": 1, "palabra": "valentía-xóchitl"}]}}